<?xml version="1.0" encoding="utf-8" ?>
<dwsync>
<file name="img_p1.jpg" server="ftp.screencraft.net.au//" local="131147050720000000" remote="132028941000000000" Dst="0" />
<file name="img_p2.jpg" server="ftp.screencraft.net.au//" local="131147050760000000" remote="132028941000000000" Dst="0" />
<file name="img_p3.jpg" server="ftp.screencraft.net.au//" local="131147050800000000" remote="132028941000000000" Dst="0" />
<file name="img_p4.jpg" server="ftp.screencraft.net.au//" local="131147050840000000" remote="132028941000000000" Dst="0" />
<file name="img_p6.jpg" server="ftp.screencraft.net.au//" local="131147050920000000" remote="132028941000000000" Dst="0" />
<file name="img_p5.jpg" server="ftp.screencraft.net.au//" local="131147050880000000" remote="132028941000000000" Dst="0" />
<file name="img_p8.jpg" server="ftp.screencraft.net.au//" local="131147051000000000" remote="132028941000000000" Dst="0" />
<file name="img_parallax2.jpg" server="ftp.screencraft.net.au//" local="131147050520000000" remote="132028941000000000" Dst="0" />
<file name="img_p7.jpg" server="ftp.screencraft.net.au//" local="131147050960000000" remote="132028941000000000" Dst="0" />
<file name="img_parallax1.jpg" server="ftp.screencraft.net.au//" local="131147050180000000" remote="132028941000000000" Dst="0" />
<file name="img_parallax3.jpg" server="ftp.screencraft.net.au//" local="131147051300000000" remote="132028941000000000" Dst="0" />
</dwsync>